Practical-4/src/Parameter.v
// =========================================================================
// Practical 4: StarCore-1 — Single-Cycle Processor in Verilog
// =========================================================================
//
// GROUP NUMBER: 10
//
// MEMBERS:
//   - Member 1 Maarij Alam, ALMMOH017
//   - Member 2 Saeed Solomon, SLMMOG032

// File        : Parameter.v
// Description : Shared compile-time parameters used across all modules.
//               Include this file at the top of every .v file:
//                   `include "../src/Parameter.v"
// =============================================================================

`ifndef PARAMETER_H_
`define PARAMETER_H_

// ---------------------------------------------------------------------------
// Memory dimensions
// ---------------------------------------------------------------------------
`define COL     16          // Data/instruction word width (bits)
`define ROW_I   16          // Instruction memory depth (words, 16 x 16-bit)
`define ROW_D    8          // Data memory depth (words,  8 x 16-bit)

// ---------------------------------------------------------------------------
// Simulation control
// Increase SIM_TIME if your test program needs more clock cycles to complete.
// At 10 ns per clock (100 MHz) each #10 is one half-period; 320 ns = 16 cycles.
// ---------------------------------------------------------------------------
`define SIM_TIME  #130      // Total simulation time for integration testbench

// ---------------------------------------------------------------------------
// Output file for data-memory dump (used in DataMemory.v $fmonitor)
// ---------------------------------------------------------------------------
`define DMEM_LOG  "./waves/dmem_log.txt"

`endif  // PARAMETER_H_

Practical-4/src/DataMemory.v
// =========================================================================
// Practical 4: StarCore-1 — Single-Cycle Processor in Verilog
// =========================================================================
//
// GROUP NUMBER: 10
//
// MEMBERS:
//   - Member 1 Maarij Alam, ALMMOH017
//   - Member 2 Saeed Solomon, SLMMOG032

// File        : DataMemory.v
// Description : Data Memory (RAM).
//               8 words × 16 bits. Contents loaded at simulation start from
//               the binary file ./test/test.data using $readmemb.
//               Writes are synchronous (positive-edge clocked).
//               Reads are combinational and gated by the mem_read enable.
//
// Task 4 — Student Implementation Required
// =============================================================================

`timescale 1ns / 1ps
`include "../src/Parameter.v"

module DataMemory (
    input        clk,

    // Shared address bus (used for both reads and writes)
    input  [15:0] mem_access_addr,  // Byte address; only lower bits used for indexing

    // Write port
    input  [15:0] mem_write_data,   // Data to store
    input        mem_write_en,      // Assert to write on the next posedge clk

    // Read port
    input        mem_read,          // Assert to enable the read output
    output [15:0] mem_read_data     // Read result; 16'd0 when mem_read is de-asserted
);

    // -------------------------------------------------------------------------
    // TODO: Declare the data memory array.
    //       It should hold `ROW_D entries, each `COL bits wide.
    //
    //       reg [`COL-1:0] memory [`ROW_D-1:0];

    reg [`COL-1:0] memory [`ROW_D-1:0];

    // -------------------------------------------------------------------------


    // -------------------------------------------------------------------------
    // TODO: Derive the word address from mem_access_addr.
    //       The data memory is 8 words deep so only 3 address bits are needed.
    //       The ALU computes a byte address; use the lower 3 bits as the index:
    //
    //           wire [2:0] ram_addr = mem_access_addr[2:0];
    //
    //       This maps byte addresses 0,1,2,3,4,5,6,7 to words 0–7.
    //       (In a full system the byte offset within a word would also be
    //       handled, but StarCore-1 only supports 16-bit aligned accesses.)

    wire [2:0] ram_addr = mem_access_addr[2:0];

    // -------------------------------------------------------------------------


    // -------------------------------------------------------------------------
    // TODO: Load the data memory from file at simulation start.
    //       The file ./test/test.data must contain one 16-bit binary value
    //       per line (8 lines total, one per word).
    //
    //       integer log_fd;
    //       initial begin
    //           $readmemb("./test/test.data", memory);
    //       end
    //
    //       Optional — add a $fmonitor to log memory contents to a file.
    //       This is useful for verifying ST instructions during simulation:
    //
    //       initial begin
    //           log_fd = $fopen(`DMEM_LOG);
    //           $fmonitor(log_fd, "t=%0t  [0]=%h [1]=%h [2]=%h [3]=%h",
    //                     $time, memory[0], memory[1], memory[2], memory[3]);
    //           `SIM_TIME;
    //           $fclose(log_fd);
    //       end

    integer log_fd;
    initial begin
        //$readmemb("./test/test.data", memory);
        $readmemb("test.data", memory);
        $display("DEBUG DataMem[0]=%b", memory[0]);  // should print 0000000000000001
        $display("DEBUG DataMem[1]=%b", memory[1]);  // should print 0000000000000010

        //these are not the problem
    end

    // -------------------------------------------------------------------------


    // -------------------------------------------------------------------------
    // TODO: Implement the synchronous write port.
    //       Write mem_write_data to memory[ram_addr] on the rising clock edge
    //       when mem_write_en is asserted.
    //
    //       always @(posedge clk) begin
    //           if (mem_write_en)
    //               memory[ram_addr] <= mem_write_data;
    //       end
    //
    //       IMPORTANT: Use non-blocking assignment (<=).

    always @(posedge clk) begin
        if (mem_write_en)
            memory[ram_addr] <= mem_write_data;
    end

    // -------------------------------------------------------------------------


    // -------------------------------------------------------------------------
    // TODO: Implement the combinational (gated) read port.
    //       When mem_read is 1, output memory[ram_addr].
    //       When mem_read is 0, output 16'd0 (prevents spurious register writes
    //       during non-LD instructions).
    //
    //       assign mem_read_data = mem_read ? memory[ram_addr] : 16'd0;

    assign mem_read_data = mem_read ? memory[ram_addr] : 16'd0;

    // -------------------------------------------------------------------------


endmodule

Practical-4/tb/DataMemory_tb.v
// =============================================================================
// EEE4120F Practical 4 — StarCore-1 Processor
// File        : DataMemory_tb.v
// Description : Testbench for the Data Memory module (Task 4).
//               Verifies synchronous write, gated combinational read,
//               write followed by immediate read, and disabled-write safety.
//
// Run:
//   iverilog -Wall -I ../src -o ../build/dm_sim ../src/DataMemory.v DataMemory_tb.v
//   cd ../test && ../build/dm_sim
//   gtkwave ../waves/dm_tb.vcd &
// =============================================================================

`timescale 1ns / 1ps
`include "../src/Parameter.v"

module DataMemory_tb;

    reg        clk;
    reg  [15:0] mem_access_addr;
    reg  [15:0] mem_write_data;
    reg        mem_write_en;
    reg        mem_read;
    wire [15:0] mem_read_data;

    DataMemory uut (
        .clk             (clk),
        .mem_access_addr (mem_access_addr),
        .mem_write_data  (mem_write_data),
        .mem_write_en    (mem_write_en),
        .mem_read        (mem_read),
        .mem_read_data   (mem_read_data)
    );

    initial clk = 1'b0;
    always  #5 clk = ~clk;

    initial begin
        $dumpfile("../waves/dm_tb.vcd");
        $dumpvars(0, DataMemory_tb);
    end

    integer fail_count;
    integer test_id;

    initial begin
        fail_count      = 0;
        test_id         = 1;
        mem_write_en    = 1'b0;
        mem_read        = 1'b0;
        mem_access_addr = 16'd0;
        mem_write_data  = 16'd0;

        $display("=== DataMemory Testbench ===");

        // ------------------------------------------------------------------
        // TEST GROUP 1: Read back initial values loaded from test.data
        // ------------------------------------------------------------------
        $display("--- Group 1: Verify $readmemb initialisation ---");

        // TODO: Read each of the 8 memory locations and verify against
        //       the known contents of your test.data file.
        //       Remember: only mem_access_addr[2:0] is used as the index.
        //       Address 16'd0 -> word 0, address 16'd2 -> word 2, etc.
        //       (Or use address 16'd0 -> word 0, address 16'd1 -> word 1,
        //        since only the lower 3 bits matter.)
        //
        //       mem_read = 1'b1;
        //       mem_access_addr = 16'd0; #5;
        //       if (mem_read_data !== 16'h0001)  // expected value from test.data line 0
        //           $display("FAIL [T%0d]: addr=0 got=0x%h exp=0x0001", test_id, mem_read_data);
        //       else
        //           $display("PASS [T%0d]", test_id);
        //       test_id = test_id + 1;
            mem_read = 1'b1;
            for (integer i = 0; i < 8; i = i + 1) begin
                mem_access_addr = i[15:0]; #10;
                $display("Reading Addr %0d: Data = %h", i, mem_read_data);
                test_id = test_id + 1;
            end

        // ------------------------------------------------------------------
        // TEST GROUP 2: Write new values to all 8 locations, then read back
        // ------------------------------------------------------------------
        $display("--- Group 2: Write then read all 8 locations ---");
        mem_write_en = 1'b1;
        for (integer i = 0; i < 8; i = i + 1) begin
            mem_access_addr = i[15:0];
            mem_write_data  = 16'hA000 + i; // Distinct value (A000, A001...)
            @(posedge clk); #1; // Wait for write to commit
        end
        mem_write_en = 1'b0;

        // Verify those writes
        mem_read = 1'b1;
        for (integer i = 0; i < 8; i = i + 1) begin
            mem_access_addr = i[15:0]; #10;
            if (mem_read_data !== (16'hA000 + i)) begin
                $display("FAIL [T%0d]: addr=%0d got=%h", test_id, i, mem_read_data);
                fail_count = fail_count + 1;
            end else
                $display("PASS [T%0d]: addr=%0d data correct", test_id, i);
            test_id = test_id + 1;
        end
        // TODO: Write a distinct value to each of the 8 addresses using
        //       mem_write_en and posedge clk, then read each back.
        //
        //       // Write to address 0
        //       mem_write_en    = 1'b1;
        //       mem_access_addr = 16'd0;
        //       mem_write_data  = 16'hABCD;
        //       @(posedge clk); #1;
        //       mem_write_en    = 1'b0;
        //
        //       // Read back from address 0
        //       mem_read = 1'b1;
        //       mem_access_addr = 16'd0; #5;
        //       if (mem_read_data !== 16'hABCD) ...
        //       test_id = test_id + 1;


        // ------------------------------------------------------------------
        // TEST GROUP 3: mem_read = 0 must produce 16'd0 output
        // ------------------------------------------------------------------
        $display("--- Group 3: mem_read disabled -> output must be 0 ---");

        // TODO: De-assert mem_read and verify the output is 16'd0 regardless
        //       of the address.
        //
        //       mem_read = 1'b0;
        //       mem_access_addr = 16'd0; #5;
        //       if (mem_read_data !== 16'd0)
        //           $display("FAIL [T%0d]: mem_read=0 but output=%h", test_id, mem_read_data);
        //       else
        //           $display("PASS [T%0d]: output = 0 when mem_read=0", test_id);
        //       test_id = test_id + 1;
        mem_read = 1'b0;
        mem_access_addr = 16'd2; #10;
        if (mem_read_data !== 16'd0) begin
            $display("FAIL [T%0d]: mem_read=0 but output=%h", test_id, mem_read_data);
            fail_count = fail_count + 1;
        end else
            $display("PASS [T%0d]: output gated to 0", test_id);
        test_id = test_id + 1;

        // ------------------------------------------------------------------
        // TEST GROUP 4: Write then immediately read on the next cycle
        // ------------------------------------------------------------------
        $display("--- Group 4: Write followed by immediate read ---");

        // TODO: Write to address 3, then on the very next cycle read back
        //       from address 3 and confirm the new value is returned.
        // Step A: Write to address 3
        mem_write_en    = 1'b1;
        mem_read        = 1'b0;
        mem_access_addr = 16'd3;
        mem_write_data  = 16'hBEEF;
        @(posedge clk); #1; // Write happens on this edge

        // Step B: Read from address 3 on the very next cycle
        mem_write_en    = 1'b0;
        mem_read        = 1'b1;
        mem_access_addr = 16'd3; 
        #5; // Wait for combinational logic to settle

        if (mem_read_data !== 16'hBEEF) begin
            $display("FAIL [T%0d]: Immediate read failed. Got=%h", test_id, mem_read_data);
            fail_count = fail_count + 1;
        end else
            $display("PASS [T%0d]: Immediate read success (Data: %h)", test_id, mem_read_data);
        
        test_id = test_id + 1;

        // ------------------------------------------------------------------
        // TEST GROUP 5: Disabled write must not alter memory
        // ------------------------------------------------------------------
        $display("--- Group 5: mem_write_en=0 must not overwrite memory ---");

        // TODO: Assert mem_write_en=0, clock one cycle, then read and confirm
        //       the previous value is unchanged.
        mem_read = 1'b1;
        mem_access_addr = 16'd4; #10;
        mem_write_data = 16'hDEAD; // Try to overwrite
        mem_write_en = 1'b0;
        @(posedge clk); #1; // Trigger clock
        
        if (mem_read_data === 16'hDEAD) begin
            $display("FAIL [T%0d]: Memory overwritten while write_en=0", test_id);
            fail_count = fail_count + 1;
        end else
            $display("PASS [T%0d]: Memory protected", test_id);
        test_id = test_id + 1;

        $display("");
        if (fail_count == 0)
            $display("=== ALL %0d TESTS PASSED ===", test_id - 1);
        else
            $display("=== %0d / %0d TESTS FAILED ===", fail_count, test_id - 1);
        $finish;
    end

endmodule

Practical-4/waves/dm_tb.vcd
$date
	Tue Apr 21 18:29:27 2026
$end
$version
	Icarus Verilog
$end
$timescale
	1ps
$end
$scope module DataMemory_tb $end
$var wire 16 ! mem_read_data [15:0] $end
$var reg 1 " clk $end
$var reg 16 # mem_access_addr [15:0] $end
$var reg 1 $ mem_read $end
$var reg 16 % mem_write_data [15:0] $end
$var reg 1 & mem_write_en $end
$var integer 32 ' fail_count [31:0] $end
$var integer 32 ( test_id [31:0] $end
$scope module uut $end
$var wire 1 " clk $end
$var wire 16 ) mem_access_addr [15:0] $end
$var wire 1 $ mem_read $end
$var wire 16 * mem_write_data [15:0] $end
$var wire 1 & mem_write_en $end
$var wire 3 + ram_addr [2:0] $end
$var wire 16 , mem_read_data [15:0] $end
$upscope $end
$scope begin $ivl_for_loop0 $end
$var integer 32 - i [31:0] $end
$upscope $end
$scope begin $ivl_for_loop1 $end
$var integer 32 . i [31:0] $end
$upscope $end
$scope begin $ivl_for_loop2 $end
$var integer 32 / i [31:0] $end
$upscope $end
$upscope $end
$enddefinitions $end
$comment Show the parameter values. $end
$dumpall
$end
#0
$dumpvars
bx /
bx .
b0 -
bx ,
b0 +
b0 *
b0 )
b1 (
b0 '
0&
b0 %
1$
b0 #
0"
bx !
$end
#5000
1"
#10000
b1 +
0"
b1 #
b1 )
b1 -
b10 (
#15000
1"
#20000
b10 +
0"
b10 #
b10 )
b10 -
b11 (
#25000
1"
#30000
b11 +
0"
b11 #
b11 )
b11 -
b100 (
#35000
1"
#40000
b100 +
0"
b100 #
b100 )
b100 -
b101 (
#45000
1"
#50000
b101 +
0"
b101 #
b101 )
b101 -
b110 (
#55000
1"
#60000
b110 +
0"
b110 #
b110 )
b110 -
b111 (
#65000
1"
#70000
b111 +
0"
b111 #
b111 )
b111 -
b1000 (
#75000
1"
#80000
b0 +
0"
b1010000000000000 %
b1010000000000000 *
b0 #
b0 )
b0 .
1&
b1000 -
b1001 (
#85000
b1010000000000000 !
b1010000000000000 ,
1"
#86000
bx !
bx ,
b1 +
b1010000000000001 %
b1010000000000001 *
b1 #
b1 )
b1 .
#90000
0"
#95000
b1010000000000001 !
b1010000000000001 ,
1"
#96000
bx !
bx ,
b10 +
b1010000000000010 %
b1010000000000010 *
b10 #
b10 )
b10 .
#100000
0"
#105000
b1010000000000010 !
b1010000000000010 ,
1"
#106000
bx !
bx ,
b11 +
b1010000000000011 %
b1010000000000011 *
b11 #
b11 )
b11 .
#110000
0"
#115000
b1010000000000011 !
b1010000000000011 ,
1"
#116000
bx !
bx ,
b100 +
b1010000000000100 %
b1010000000000100 *
b100 #
b100 )
b100 .
#120000
0"
#125000
b1010000000000100 !
b1010000000000100 ,
1"
#126000
bx !
bx ,
b101 +
b1010000000000101 %
b1010000000000101 *
b101 #
b101 )
b101 .
#130000
0"
#135000
b1010000000000101 !
b1010000000000101 ,
1"
#136000
bx !
bx ,
b110 +
b1010000000000110 %
b1010000000000110 *
b110 #
b110 )
b110 .
#140000
0"
#145000
b1010000000000110 !
b1010000000000110 ,
1"
#146000
bx !
bx ,
b111 +
b1010000000000111 %
b1010000000000111 *
b111 #
b111 )
b111 .
#150000
0"
#155000
b1010000000000111 !
b1010000000000111 ,
1"
#156000
b1010000000000000 !
b1010000000000000 ,
b0 +
b0 #
b0 )
b0 /
0&
b1000 .
#160000
0"
#165000
1"
#166000
b1010000000000001 !
b1010000000000001 ,
b1 +
b1 #
b1 )
b1 /
b1010 (
#170000
0"
#175000
1"
#176000
b1010000000000010 !
b1010000000000010 ,
b10 +
b10 #
b10 )
b10 /
b1011 (
#180000
0"
#185000
1"
#186000
b1010000000000011 !
b1010000000000011 ,
b11 +
b11 #
b11 )
b11 /
b1100 (
#190000
0"
#195000
1"
#196000
b1010000000000100 !
b1010000000000100 ,
b100 +
b100 #
b100 )
b100 /
b1101 (
#200000
0"
#205000
1"
#206000
b1010000000000101 !
b1010000000000101 ,
b101 +
b101 #
b101 )
b101 /
b1110 (
#210000
0"
#215000
1"
#216000
b1010000000000110 !
b1010000000000110 ,
b110 +
b110 #
b110 )
b110 /
b1111 (
#220000
0"
#225000
1"
#226000
b1010000000000111 !
b1010000000000111 ,
b111 +
b111 #
b111 )
b111 /
b10000 (
#230000
0"
#235000
1"
#236000
b10 +
b0 !
b0 ,
b10 #
b10 )
0$
b1000 /
b10001 (
#240000
0"
#245000
1"
#246000
b11 +
b1011111011101111 %
b1011111011101111 *
b11 #
b11 )
1&
b10010 (
#250000
0"
#255000
1"
#256000
b1011111011101111 !
b1011111011101111 ,
1$
0&
#260000
0"
#261000
b1010000000000100 !
b1010000000000100 ,
b100 +
b100 #
b100 )
b10011 (
#265000
1"
#270000
0"
#271000
b1101111010101101 %
b1101111010101101 *
#275000
1"
#276000
b10100 (
