Practical-4/src/Parameter.v
// =========================================================================
// Practical 4: StarCore-1 — Single-Cycle Processor in Verilog
// =========================================================================
//
// GROUP NUMBER: 10
//
// MEMBERS:
//   - Member 1 Maarij Alam, ALMMOH017
//   - Member 2 Saeed Solomon, SLMMOG032

// File        : Parameter.v
// Description : Shared compile-time parameters used across all modules.
//               Include this file at the top of every .v file:
//                   `include "../src/Parameter.v"
// =============================================================================

`ifndef PARAMETER_H_
`define PARAMETER_H_

// ---------------------------------------------------------------------------
// Memory dimensions
// ---------------------------------------------------------------------------
`define COL     16          // Data/instruction word width (bits)
`define ROW_I   16          // Instruction memory depth (words, 16 x 16-bit)
`define ROW_D    8          // Data memory depth (words,  8 x 16-bit)

// ---------------------------------------------------------------------------
// Simulation control
// Increase SIM_TIME if your test program needs more clock cycles to complete.
// At 10 ns per clock (100 MHz) each #10 is one half-period; 320 ns = 16 cycles.
// ---------------------------------------------------------------------------
`define SIM_TIME  #130      // Total simulation time for integration testbench

// ---------------------------------------------------------------------------
// Output file for data-memory dump (used in DataMemory.v $fmonitor)
// ---------------------------------------------------------------------------
`define DMEM_LOG  "./waves/dmem_log.txt"

`endif  // PARAMETER_H_

Practical-4/src/InstructionMemory.v
// =========================================================================
// Practical 4: StarCore-1 — Single-Cycle Processor in Verilog
// =========================================================================
//
// GROUP NUMBER: 10
//
// MEMBERS:
//   - Member 1 Maarij Alam, ALMMOH017
//   - Member 2 Saeed Solomon, SLMMOG032

// File        : InstructionMemory.v
// Description : Instruction Memory (ROM).
//               16 words × 16 bits. Contents loaded at simulation start from
//               the binary file ./test/test.prog using $readmemb.
//               This is a purely combinational module — the instruction output
//               updates immediately when the PC changes. No clock input.
//
// Task 3 — Student Implementation Required
// =============================================================================

`timescale 1ns / 1ps
`include "../src/Parameter.v"

module InstructionMemory (
    input  [15:0] pc,           // Program Counter (byte address)
    output [15:0] instruction   // Fetched 16-bit instruction word
);

    // -------------------------------------------------------------------------
    // TODO: Declare the instruction memory array.
    //       It should hold `ROW_I entries, each `COL bits wide.
    //
    //       reg [`COL-1:0] memory [`ROW_I-1:0];

    reg [`COL-1:0] memory [`ROW_I-1:0];

    // -------------------------------------------------------------------------


    // -------------------------------------------------------------------------
    // TODO: Derive the word address from the byte-addressed PC.
    //
    //       Because each instruction is 16 bits (2 bytes) wide, and the PC
    //       increments by 2 each cycle, the word index into the ROM is:
    //
    //           wire [3:0] rom_addr = pc[4:1];
    //
    //       This discards the byte-select bit (pc[0], always 0 for aligned
    //       accesses) and maps the byte address to a word index:
    //           PC=0x0000 -> rom_addr=0
    //           PC=0x0002 -> rom_addr=1
    //           PC=0x0004 -> rom_addr=2   ... and so on.

    wire [3:0] rom_addr = pc[4:1];

    // -------------------------------------------------------------------------


    // -------------------------------------------------------------------------
    // TODO: Load the instruction memory contents from file at simulation start.
    //       The file ./test/test.prog must contain one 16-bit binary value
    //       per line (e.g. 0010000001010000).
    //
    //       initial begin
    //           $readmemb("./test/test.prog", memory, 0, 14);
    //       end
    //
    //       Note: the third and fourth arguments (0, 14) specify the start and
    //       end indices in the array to fill. Adjust if your program is longer.

    initial begin
        //$readmemb("./test/test.prog", memory, 0, 14);
        //$readmemb("test/test.prog", memory);
        $readmemb("test.prog", memory, 0, 14);
    end

    // -------------------------------------------------------------------------


    // -------------------------------------------------------------------------
    // TODO: Drive the instruction output with a continuous assignment.
    //       The output must update combinationally whenever rom_addr changes.
    //
    //       assign instruction = memory[rom_addr];

    assign instruction = memory[rom_addr];

    // -------------------------------------------------------------------------


endmodule

Practical-4/tb/InstructionMemory_tb.v
`timescale 1ns / 1ps
`include "../src/Parameter.v"

module InstructionMemory_tb;

    reg  [15:0] pc;
    wire [15:0] instruction;

    // Instantiate the Unit Under Test (UUT)
    InstructionMemory uut (
        .pc(pc), 
        .instruction(instruction)
    );

    // Waveform dump for GTKWave report requirements [cite: 24]
    initial begin
        $dumpfile("../waves/im_tb.vcd");
        $dumpvars(0, InstructionMemory_tb);
    end

    integer fail_count;
    integer test_id;
    
    // Array to hold the "Answer Key" for verification
    reg [15:0] expected [0:14];

    initial begin
        fail_count = 0;
        test_id    = 1;

        $display("=== InstructionMemory Testbench ===");

        // --- Step 1: Manual Mapping of your test.prog binary ---
        expected[0]  = 16'b0000010000000000;
        expected[1]  = 16'b0000010001000001;
        expected[2]  = 16'b0010000001010000;
        expected[3]  = 16'b0001001010000000;
        expected[4]  = 16'b0011000001010000;
        expected[5]  = 16'b0111000001010000;
        expected[6]  = 16'b1000000001010000;
        expected[7]  = 16'b1001000001010000;
        expected[8]  = 16'b0010000000000000;
        expected[9]  = 16'b1011000001000001;
        expected[10] = 16'b1100000001000000;
        expected[11] = 16'b1101000000000000;
        expected[12] = 16'b0000000000000000;
        expected[13] = 16'b0000000000000000;
        expected[14] = 16'b0000000000000000;

        // --- Step 2: Walk PC through byte-addresses ---
        // Every StarCore instruction is 2 bytes (16 bits) [cite: 80, 107]
        for (integer j = 0; j < 15; j = j + 1) begin
            pc = j * 2; 
            #5; // Wait for combinational logic to settle [cite: 197]
            
            if (instruction !== expected[j]) begin
                $display("FAIL [T%0d]: PC=%0d got %b exp %b", 
                         test_id, pc, instruction, expected[j]);
                fail_count = fail_count + 1;
            end else begin
                $display("PASS [T%0d]: PC=%0d instruction matched", test_id, pc);
            end
            test_id = test_id + 1;
        end

        // --- Step 3: Summary ---
        $display("");
        if (fail_count == 0)
            $display("=== ALL %0d TESTS PASSED ===", test_id - 1);
        else
            $display("=== %0d / %0d TESTS FAILED ===", fail_count, test_id - 1);
        
        $finish; // End simulation [cite: 150]
    end

endmodule

Practical-4/waves/im_tb.vcd
$date
	Tue Apr 21 18:29:27 2026
$end
$version
	Icarus Verilog
$end
$timescale
	1ps
$end
$scope module InstructionMemory_tb $end
$var wire 16 ! instruction [15:0] $end
$var reg 16 " pc [15:0] $end
$var integer 32 # fail_count [31:0] $end
$var integer 32 $ test_id [31:0] $end
$scope module uut $end
$var wire 16 % instruction [15:0] $end
$var wire 16 & pc [15:0] $end
$var wire 4 ' rom_addr [3:0] $end
$upscope $end
$scope begin $ivl_for_loop0 $end
$var integer 32 ( j [31:0] $end
$upscope $end
$upscope $end
$enddefinitions $end
$comment Show the parameter values. $end
$dumpall
$end
#0
$dumpvars
b0 (
b0 '
b0 &
b10000000000 %
b1 $
b0 #
b0 "
b10000000000 !
$end
#5000
b10001000001 !
b10001000001 %
b1 '
b10 "
b10 &
b1 (
b10 $
#10000
b10000001010000 !
b10000001010000 %
b10 '
b100 "
b100 &
b10 (
b11 $
#15000
b1001010000000 !
b1001010000000 %
b11 '
b110 "
b110 &
b11 (
b100 $
#20000
b11000001010000 !
b11000001010000 %
b100 '
b1000 "
b1000 &
b100 (
b101 $
#25000
b111000001010000 !
b111000001010000 %
b101 '
b1010 "
b1010 &
b101 (
b110 $
#30000
b1000000001010000 !
b1000000001010000 %
b110 '
b1100 "
b1100 &
b110 (
b111 $
#35000
b1001000001010000 !
b1001000001010000 %
b111 '
b1110 "
b1110 &
b111 (
b1000 $
#40000
b10000000000000 !
b10000000000000 %
b1000 '
b10000 "
b10000 &
b1000 (
b1001 $
#45000
b1011000001000001 !
b1011000001000001 %
b1001 '
b10010 "
b10010 &
b1001 (
b1010 $
#50000
b1100000001000000 !
b1100000001000000 %
b1010 '
b10100 "
b10100 &
b1010 (
b1011 $
#55000
b1101000000000000 !
b1101000000000000 %
b1011 '
b10110 "
b10110 &
b1011 (
b1100 $
#60000
b0 !
b0 %
b1100 '
b11000 "
b11000 &
b1100 (
b1101 $
#65000
b1101 '
b11010 "
b11010 &
b1101 (
b1110 $
#70000
b1110 '
b11100 "
b11100 &
b1110 (
b1111 $
#75000
b1111 (
b10000 $
